{
  "upsc": {
    "timestamp_utc": "2026-07-18T22:28:12Z",
    "status_code": 0,
    "latency_ms": 10479,
    "up": false
  },
  "ssc": {
    "timestamp_utc": "2026-07-18T22:28:12Z",
    "status_code": 200,
    "latency_ms": 1255,
    "up": true
  },
  "nta": {
    "timestamp_utc": "2026-07-18T22:28:12Z",
    "status_code": 200,
    "latency_ms": 1550,
    "up": true
  },
  "ibps": {
    "timestamp_utc": "2026-07-18T22:28:12Z",
    "status_code": 0,
    "latency_ms": 941,
    "up": false
  },
  "rrb": {
    "timestamp_utc": "2026-07-18T22:28:12Z",
    "status_code": 0,
    "latency_ms": 497,
    "up": false
  },
  "rrb_apply": {
    "timestamp_utc": "2026-07-18T22:28:12Z",
    "status_code": 404,
    "latency_ms": 1173,
    "up": false
  },
  "indiapost_gds": {
    "timestamp_utc": "2026-07-18T22:28:12Z",
    "status_code": 0,
    "latency_ms": 907,
    "up": false
  },
  "rbi": {
    "timestamp_utc": "2026-07-18T22:28:12Z",
    "status_code": 200,
    "latency_ms": 1064,
    "up": true
  },
  "sbi": {
    "timestamp_utc": "2026-07-18T22:28:12Z",
    "status_code": 200,
    "latency_ms": 1206,
    "up": true
  },
  "uppsc": {
    "timestamp_utc": "2026-07-18T22:28:12Z",
    "status_code": 404,
    "latency_ms": 1296,
    "up": false
  },
  "upsssc": {
    "timestamp_utc": "2026-07-18T22:28:12Z",
    "status_code": 0,
    "latency_ms": 10272,
    "up": false
  },
  "bpsc": {
    "timestamp_utc": "2026-07-18T22:28:12Z",
    "status_code": 0,
    "latency_ms": 2020,
    "up": false
  },
  "mppsc": {
    "timestamp_utc": "2026-07-18T22:28:12Z",
    "status_code": 403,
    "latency_ms": 978,
    "up": false
  },
  "rpsc": {
    "timestamp_utc": "2026-07-18T22:28:12Z",
    "status_code": 0,
    "latency_ms": 10270,
    "up": false
  },
  "mpsc": {
    "timestamp_utc": "2026-07-18T22:28:12Z",
    "status_code": 200,
    "latency_ms": 723,
    "up": true
  },
  "tnpsc": {
    "timestamp_utc": "2026-07-18T22:28:12Z",
    "status_code": 0,
    "latency_ms": 10261,
    "up": false
  },
  "wbpsc": {
    "timestamp_utc": "2026-07-18T22:28:12Z",
    "status_code": 0,
    "latency_ms": 1248,
    "up": false
  }
}